opal_tools_sdk/__init__.py
opal_tools_sdk/_registry.py
opal_tools_sdk/auth.py
opal_tools_sdk/decorators.py
opal_tools_sdk/models.py
opal_tools_sdk/service.py
opal_tools_sdk-0.1.2.dev2.dist-info/METADATA
opal_tools_sdk-0.1.2.dev2.dist-info/WHEEL
opal_tools_sdk-0.1.2.dev2.dist-info/top_level.txt
opal_tools_sdk-0.1.2.dev2.dist-info/RECORD
